[
  { "lng": 90.4125, "lat": 23.8103, "city": "Dhaka", "country": "Bangladesh", "population_density": 44500, "income_index": 0.18, "infra_score": 0.04, "gap_score": 0.93 },
  { "lng": 3.3792, "lat": 6.5244, "city": "Lagos", "country": "Nigeria", "population_density": 20000, "income_index": 0.2, "infra_score": 0.06, "gap_score": 0.88 },
  { "lng": 106.8456, "lat": -6.2088, "city": "Jakarta", "country": "Indonesia", "population_density": 15600, "income_index": 0.28, "infra_score": 0.12, "gap_score": 0.79 },
  { "lng": 74.3436, "lat": 31.5497, "city": "Lahore", "country": "Pakistan", "population_density": 11100, "income_index": 0.22, "infra_score": 0.07, "gap_score": 0.82 },
  { "lng": 72.8777, "lat": 19.076, "city": "Mumbai", "country": "India", "population_density": 20667, "income_index": 0.31, "infra_score": 0.15, "gap_score": 0.74 },
  { "lng": 77.209, "lat": 28.6139, "city": "Delhi", "country": "India", "population_density": 11312, "income_index": 0.29, "infra_score": 0.13, "gap_score": 0.75 },
  { "lng": 88.3639, "lat": 22.5726, "city": "Kolkata", "country": "India", "population_density": 24252, "income_index": 0.24, "infra_score": 0.1, "gap_score": 0.81 },
  { "lng": 120.9842, "lat": 14.5995, "city": "Manila", "country": "Philippines", "population_density": 71263, "income_index": 0.27, "infra_score": 0.09, "gap_score": 0.87 },
  { "lng": 67.0099, "lat": 24.8607, "city": "Karachi", "country": "Pakistan", "population_density": 24000, "income_index": 0.2, "infra_score": 0.05, "gap_score": 0.89 },
  { "lng": 15.2663, "lat": -4.3317, "city": "Kinshasa", "country": "DR Congo", "population_density": 8000, "income_index": 0.09, "infra_score": 0.02, "gap_score": 0.91 },
  { "lng": 36.8219, "lat": -1.2921, "city": "Nairobi", "country": "Kenya", "population_density": 4700, "income_index": 0.24, "infra_score": 0.08, "gap_score": 0.77 },
  { "lng": -0.1969, "lat": 5.6037, "city": "Accra", "country": "Ghana", "population_density": 3500, "income_index": 0.25, "infra_score": 0.06, "gap_score": 0.74 },
  { "lng": 39.2083, "lat": -6.7924, "city": "Dar es Salaam", "country": "Tanzania", "population_density": 3100, "income_index": 0.15, "infra_score": 0.04, "gap_score": 0.84 },
  { "lng": 32.5825, "lat": 0.3476, "city": "Kampala", "country": "Uganda", "population_density": 2400, "income_index": 0.13, "infra_score": 0.03, "gap_score": 0.86 },
  { "lng": 38.7578, "lat": 9.145, "city": "Addis Ababa", "country": "Ethiopia", "population_density": 5200, "income_index": 0.11, "infra_score": 0.05, "gap_score": 0.88 },
  { "lng": 18.4241, "lat": -33.9249, "city": "Cape Town Informal", "country": "South Africa", "population_density": 6800, "income_index": 0.19, "infra_score": 0.09, "gap_score": 0.78 },
  { "lng": -77.0428, "lat": -12.0464, "city": "Lima", "country": "Peru", "population_density": 3200, "income_index": 0.3, "infra_score": 0.11, "gap_score": 0.71 },
  { "lng": -74.0721, "lat": 4.7110, "city": "Bogotá", "country": "Colombia", "population_density": 4300, "income_index": 0.32, "infra_score": 0.25, "gap_score": 0.55 },
  { "lng": -46.6333, "lat": -23.5505, "city": "São Paulo (periphery)", "country": "Brazil", "population_density": 7800, "income_index": 0.28, "infra_score": 0.14, "gap_score": 0.69 },
  { "lng": -58.3816, "lat": -34.6037, "city": "Buenos Aires (outskirts)", "country": "Argentina", "population_density": 4100, "income_index": 0.33, "infra_score": 0.13, "gap_score": 0.65 },
  { "lng": -99.1332, "lat": 19.4326, "city": "Mexico City (periphery)", "country": "Mexico", "population_density": 5900, "income_index": 0.3, "infra_score": 0.1, "gap_score": 0.72 },
  { "lng": 28.9784, "lat": 41.0082, "city": "Istanbul (outskirts)", "country": "Turkey", "population_density": 2800, "income_index": 0.38, "infra_score": 0.18, "gap_score": 0.58 },
  { "lng": 31.2357, "lat": 30.0444, "city": "Cairo", "country": "Egypt", "population_density": 19376, "income_index": 0.25, "infra_score": 0.1, "gap_score": 0.8 },
  { "lng": 44.3661, "lat": 33.3152, "city": "Baghdad", "country": "Iraq", "population_density": 3200, "income_index": 0.27, "infra_score": 0.08, "gap_score": 0.73 },
  { "lng": 51.4231, "lat": 35.6892, "city": "Tehran", "country": "Iran", "population_density": 11800, "income_index": 0.35, "infra_score": 0.2, "gap_score": 0.61 },
  { "lng": 104.9282, "lat": 11.5564, "city": "Phnom Penh", "country": "Cambodia", "population_density": 2800, "income_index": 0.19, "infra_score": 0.04, "gap_score": 0.87 },
  { "lng": 102.6331, "lat": 17.9757, "city": "Vientiane", "country": "Laos", "population_density": 900, "income_index": 0.2, "infra_score": 0.03, "gap_score": 0.83 },
  { "lng": 96.1951, "lat": 16.8661, "city": "Yangon", "country": "Myanmar", "population_density": 6000, "income_index": 0.17, "infra_score": 0.04, "gap_score": 0.89 },
  { "lng": 85.3240, "lat": 27.7172, "city": "Kathmandu", "country": "Nepal", "population_density": 20300, "income_index": 0.16, "infra_score": 0.05, "gap_score": 0.9 },
  { "lng": 79.8612, "lat": 6.9271, "city": "Colombo", "country": "Sri Lanka", "population_density": 3400, "income_index": 0.26, "infra_score": 0.1, "gap_score": 0.73 },
  { "lng": 4.9041, "lat": 52.3676, "city": "Amsterdam", "country": "Netherlands", "population_density": 5300, "income_index": 0.88, "infra_score": 0.97, "gap_score": 0.04 },
  { "lng": 12.5683, "lat": 55.6761, "city": "Copenhagen", "country": "Denmark", "population_density": 6900, "income_index": 0.9, "infra_score": 0.95, "gap_score": 0.05 },
  { "lng": 139.6917, "lat": 35.6895, "city": "Tokyo", "country": "Japan", "population_density": 6158, "income_index": 0.85, "infra_score": 0.91, "gap_score": 0.07 },
  { "lng": 103.8198, "lat": 1.3521, "city": "Singapore", "country": "Singapore", "population_density": 7804, "income_index": 0.91, "infra_score": 0.88, "gap_score": 0.08 },
  { "lng": 114.1694, "lat": 22.3193, "city": "Hong Kong", "country": "China", "population_density": 6777, "income_index": 0.87, "infra_score": 0.89, "gap_score": 0.07 },
  { "lng": 2.3522, "lat": 48.8566, "city": "Paris", "country": "France", "population_density": 21000, "income_index": 0.86, "infra_score": 0.85, "gap_score": 0.09 },
  { "lng": 13.4050, "lat": 52.5200, "city": "Berlin", "country": "Germany", "population_density": 4100, "income_index": 0.84, "infra_score": 0.88, "gap_score": 0.07 },
  { "lng": -0.1276, "lat": 51.5074, "city": "London (inner)", "country": "UK", "population_density": 5500, "income_index": 0.87, "infra_score": 0.72, "gap_score": 0.18 },
  { "lng": -87.6298, "lat": 41.8781, "city": "Chicago", "country": "USA", "population_density": 4400, "income_index": 0.75, "infra_score": 0.45, "gap_score": 0.38 },
  { "lng": -118.2437, "lat": 34.0522, "city": "Los Angeles", "country": "USA", "population_density": 3200, "income_index": 0.78, "infra_score": 0.22, "gap_score": 0.62 },
  { "lng": -73.9857, "lat": 40.7484, "city": "New York", "country": "USA", "population_density": 10900, "income_index": 0.82, "infra_score": 0.71, "gap_score": 0.2 },
  { "lng": 37.6173, "lat": 55.7558, "city": "Moscow", "country": "Russia", "population_density": 4900, "income_index": 0.55, "infra_score": 0.6, "gap_score": 0.28 },
  { "lng": 116.4074, "lat": 39.9042, "city": "Beijing", "country": "China", "population_density": 1300, "income_index": 0.58, "infra_score": 0.55, "gap_score": 0.3 },
  { "lng": 121.4737, "lat": 31.2304, "city": "Shanghai", "country": "China", "population_density": 3800, "income_index": 0.62, "infra_score": 0.58, "gap_score": 0.27 },
  { "lng": 126.9780, "lat": 37.5665, "city": "Seoul", "country": "South Korea", "population_density": 16000, "income_index": 0.82, "infra_score": 0.82, "gap_score": 0.1 },
  { "lng": 100.5018, "lat": 13.7563, "city": "Bangkok", "country": "Thailand", "population_density": 5300, "income_index": 0.41, "infra_score": 0.24, "gap_score": 0.59 },
  { "lng": 108.2022, "lat": 16.0544, "city": "Da Nang", "country": "Vietnam", "population_density": 1100, "income_index": 0.29, "infra_score": 0.06, "gap_score": 0.77 },
  { "lng": 105.8342, "lat": 21.0278, "city": "Hanoi", "country": "Vietnam", "population_density": 2100, "income_index": 0.31, "infra_score": 0.12, "gap_score": 0.72 },
  { "lng": -17.4441, "lat": 14.6928, "city": "Dakar", "country": "Senegal", "population_density": 5700, "income_index": 0.17, "infra_score": 0.04, "gap_score": 0.88 },
  { "lng": -13.6773, "lat": 9.6412, "city": "Conakry", "country": "Guinea", "population_density": 3200, "income_index": 0.1, "infra_score": 0.02, "gap_score": 0.93 },
  { "lng": 2.1354, "lat": 6.3703, "city": "Cotonou", "country": "Benin", "population_density": 7100, "income_index": 0.14, "infra_score": 0.05, "gap_score": 0.87 },
  { "lng": -1.0232, "lat": 7.9465, "city": "Kumasi", "country": "Ghana", "population_density": 3900, "income_index": 0.22, "infra_score": 0.06, "gap_score": 0.8 },
  { "lng": 32.5599, "lat": 15.5007, "city": "Khartoum", "country": "Sudan", "population_density": 2600, "income_index": 0.14, "infra_score": 0.04, "gap_score": 0.86 },
  { "lng": -8.0029, "lat": 12.3714, "city": "Bamako", "country": "Mali", "population_density": 4500, "income_index": 0.1, "infra_score": 0.02, "gap_score": 0.92 },
  { "lng": 2.3158, "lat": 13.5137, "city": "Niamey", "country": "Niger", "population_density": 2800, "income_index": 0.08, "infra_score": 0.01, "gap_score": 0.95 }
]
